climetlab_google_drive_source
