Metadata-Version: 2.1
Name: climetlab-google-drive-source
Version: 0.1.5
Summary: A source plugin for climetlab for the source google-drive
Home-page: http://github.com/ecmwf-lab/climetlab-google-drive-source
Author: Florian Pinault
Author-email: Florian.Pinault@ecmwf.int
License: Apache License Version 2.0
Keywords: meteorology
Platform: UNKNOWN
Classifier: Development Status :: 3 - Alpha
Classifier: Intended Audience :: Developers
Classifier: License :: OSI Approved :: Apache Software License
Classifier: Programming Language :: Python :: 3
Classifier: Programming Language :: Python :: 3.8
Classifier: Programming Language :: Python :: 3.9
Classifier: Programming Language :: Python :: 3.10
Classifier: Programming Language :: Python :: Implementation :: CPython
Classifier: Programming Language :: Python :: Implementation :: PyPy
Classifier: Operating System :: OS Independent
